setup.py
paynova_api_python_client/__init__.py
paynova_api_python_client/exceptions.py
paynova_api_python_client/paynova.py
paynova_api_python_client.egg-info/PKG-INFO
paynova_api_python_client.egg-info/SOURCES.txt
paynova_api_python_client.egg-info/dependency_links.txt
paynova_api_python_client.egg-info/entry_points.txt
paynova_api_python_client.egg-info/requires.txt
paynova_api_python_client.egg-info/top_level.txt
tests/__init__.py
tests/base.py
tests/test_paynova.py
tests/test_paynova_services.py