Metadata-Version: 1.1
Name: paynova-api-python-client
Version: 0.1.0
Summary: Python client for Paynova's API.
Home-page: https://github.com/akolpakov/paynova-api-python-client
Author: Andrey Kolpakov
Author-email: aakolpakov@gmail.com
License: MIT
Keywords: paynova API python client
Platform: UNKNOWN
Classifier: Development Status :: 4 - Beta
Classifier: Intended Audience :: Developers
Classifier: License :: OSI Approved :: MIT License
Classifier: Natural Language :: English
Classifier: Operating System :: Unix
Classifier: Programming Language :: Python :: 2.7
Classifier: Programming Language :: Python :: 3.4
Classifier: Programming Language :: Python :: Implementation :: PyPy
Classifier: Operating System :: OS Independent
